setup.cfg
setup.py
pluggable/__init__.py
pluggable.egg-info/PKG-INFO
pluggable.egg-info/SOURCES.txt
pluggable.egg-info/dependency_links.txt
pluggable.egg-info/top_level.txt